vantage6/backend/common/__build__
vantage6/backend/common/__init__.py
vantage6/backend/common/_version.py
vantage6/backend/common/base.py
vantage6/backend/common/globals.py
vantage6/backend/common/jsonable.py
vantage6/backend/common/mail_service.py
vantage6/backend/common/metrics.py
vantage6/backend/common/permission.py
vantage6/backend/common/permission_models.py
vantage6/backend/common/services_resources.py
vantage6/backend/common/session.py
vantage6/backend/common/test_context.py
vantage6/backend/common/resource/__init__.py
vantage6/backend/common/resource/error_handling.py
vantage6/backend/common/resource/input_schema.py
vantage6/backend/common/resource/output_schema.py
vantage6/backend/common/resource/pagination.py
vantage6/backend/common/resource/role.py
vantage6_backend_common-4.13.6.dist-info/METADATA
vantage6_backend_common-4.13.6.dist-info/WHEEL
vantage6_backend_common-4.13.6.dist-info/top_level.txt
vantage6_backend_common-4.13.6.dist-info/RECORD
