Metadata-Version: 2.4
Name: vantage6_backend_common
Version: 4.13.6
Summary: Vantage6 common backend functionalities
Home-page: https://github.com/vantage6/vantage6
Requires-Python: >=3.10
Requires-Dist: flask==3.1.1
Requires-Dist: flask-mail==0.9.1
Requires-Dist: Flask-RESTful==0.3.10
Requires-Dist: marshmallow==3.26.2
Requires-Dist: marshmallow-sqlalchemy==0.29.0
Requires-Dist: SQLAlchemy==1.4.46
Requires-Dist: prometheus-client==0.21.1
Requires-Dist: vantage6-common==4.13.6
Provides-Extra: dev
Requires-Dist: coverage==6.4.4; extra == "dev"
Dynamic: description
Dynamic: description-content-type
Dynamic: home-page
Dynamic: provides-extra
Dynamic: requires-dist
Dynamic: requires-python
Dynamic: summary
